hero/__init__.py
hero/__main__.py
hero/cache.py
hero/checks.py
hero/cli.py
hero/cog.py
hero/command.py
hero/conf.py
hero/controller.py
hero/core.py
hero/db.py
hero/django_settings.py
hero/errors.py
hero/fields.py
hero/i18n.py
hero/logging.py
hero/main.py
hero/models.py
hero/permissions.py
hero/perms.py
hero/strings.py
hero/utils.py
hero/extensions/essentials/__init__.py
hero/extensions/essentials/cogs.py
discord_hero-0.1.0b8.dist-info/LICENSE
discord_hero-0.1.0b8.dist-info/LICENSE.Apache-2.0
discord_hero-0.1.0b8.dist-info/LICENSE.MIT
discord_hero-0.1.0b8.dist-info/METADATA
discord_hero-0.1.0b8.dist-info/WHEEL
discord_hero-0.1.0b8.dist-info/entry_points.txt
discord_hero-0.1.0b8.dist-info/top_level.txt
discord_hero-0.1.0b8.dist-info/RECORD
