Metadata-Version: 2.1
Name: discord-hero
Version: 0.1.0b8
Summary: discord-hero is an asynchronous, fully modular Discord bot framework that comes with batteries included, allowing you to write powerful Discord applications easily and quickly.
Home-page: https://github.com/discord-hero/discord-hero
Author: monospacedmagic
Author-email: luci@monospacedmagic.dev
License: Apache-2.0 OR MIT
Keywords: discord bot framework django
Platform: UNKNOWN
Classifier: Development Status :: 4 - Beta
Classifier: Environment :: Console
Classifier: Environment :: Other Environment
Classifier: Environment :: Web Environment
Classifier: Framework :: AsyncIO
Classifier: Framework :: Django
Classifier: Framework :: Django :: 3.0
Classifier: Intended Audience :: Developers
Classifier: Intended Audience :: End Users/Desktop
Classifier: License :: OSI Approved :: Apache Software License
Classifier: License :: OSI Approved :: MIT License
Classifier: Natural Language :: English
Classifier: Operating System :: OS Independent
Classifier: Programming Language :: Python
Classifier: Programming Language :: Python :: 3
Classifier: Programming Language :: Python :: 3 :: Only
Classifier: Programming Language :: Python :: 3.7
Classifier: Programming Language :: Python :: 3.8
Classifier: Topic :: Communications :: Chat
Classifier: Topic :: Software Development :: Libraries :: Application Frameworks
Classifier: Topic :: Software Development :: Libraries :: Python Modules
Requires-Python: >= 3.7.0
Requires-Dist: django
Requires-Dist: discord.py
Requires-Dist: aiocache
Requires-Dist: click
Requires-Dist: aiologger
Requires-Dist: aiofiles
Requires-Dist: python-dotenv
Requires-Dist: uvloop ; sys_platform != "win32" and implementation_name == "cpython"
Requires-Dist: colorama ; sys_platform == "win32"
Provides-Extra: postgresql
Requires-Dist: psycopg2 ; extra == 'postgresql'
Provides-Extra: redis
Requires-Dist: aioredis (>=1.0.0) ; extra == 'redis'
